YouDontKnowJsX6/README.md
YouDontKnowJsX6/__init__.py
YouDontKnowJsX6/__main__.py
YouDontKnowJsX6/file.epub
YouDontKnowJsX6/index.html
YouDontKnowJsX6/css/__init__.py
YouDontKnowJsX6/css/annotations.css
YouDontKnowJsX6/css/main.css
YouDontKnowJsX6/css/normalize.css
YouDontKnowJsX6/css/popup.css
YouDontKnowJsX6/font/__init__.py
YouDontKnowJsX6/font/fontello.eot
YouDontKnowJsX6/font/fontello.svg
YouDontKnowJsX6/font/fontello.ttf
YouDontKnowJsX6/font/fontello.woff
YouDontKnowJsX6/img/__init__.py
YouDontKnowJsX6/img/annotator-glyph-sprite.png
YouDontKnowJsX6/img/annotator-icon-sprite.png
YouDontKnowJsX6/img/apple-touch-icon.png
YouDontKnowJsX6/img/cancelfullscreen.png
YouDontKnowJsX6/img/close.png
YouDontKnowJsX6/img/fullscreen.png
YouDontKnowJsX6/img/loader.gif
YouDontKnowJsX6/img/menu-icon.png
YouDontKnowJsX6/img/save.png
YouDontKnowJsX6/img/saved.png
YouDontKnowJsX6/img/settings-s.png
YouDontKnowJsX6/img/settings.png
YouDontKnowJsX6/img/star.png
YouDontKnowJsX6/js/__init__.py
YouDontKnowJsX6/js/epub.js
YouDontKnowJsX6/js/epub.min.js
YouDontKnowJsX6/js/epub.min.map
YouDontKnowJsX6/js/hooks.min.js
YouDontKnowJsX6/js/hooks.min.map
YouDontKnowJsX6/js/reader.js
YouDontKnowJsX6/js/reader.js.map
YouDontKnowJsX6/js/reader.min.js
YouDontKnowJsX6/js/reader.min.map
YouDontKnowJsX6/js/hooks/__init__.py
YouDontKnowJsX6/js/hooks/extensions/__init__.py
YouDontKnowJsX6/js/hooks/extensions/highlight.js
YouDontKnowJsX6/js/libs/__init__.py
YouDontKnowJsX6/js/libs/jquery.min.js
YouDontKnowJsX6/js/libs/localforage.min.js
YouDontKnowJsX6/js/libs/screenfull.js
YouDontKnowJsX6/js/libs/screenfull.min.js
YouDontKnowJsX6/js/libs/zip.min.js
YouDontKnowJsX6/js/plugins/__init__.py
YouDontKnowJsX6/js/plugins/hypothesis.js
YouDontKnowJsX6/js/plugins/search.js
you_dont_know_js_x6-2024.3.2.0.dist-info/METADATA
you_dont_know_js_x6-2024.3.2.0.dist-info/WHEEL
you_dont_know_js_x6-2024.3.2.0.dist-info/entry_points.txt
you_dont_know_js_x6-2024.3.2.0.dist-info/top_level.txt
you_dont_know_js_x6-2024.3.2.0.dist-info/RECORD
